LICENSE
MANIFEST.in
README.md
setup.cfg
setup.py
incore_otp.egg-info/PKG-INFO
incore_otp.egg-info/SOURCES.txt
incore_otp.egg-info/dependency_links.txt
incore_otp.egg-info/top_level.txt
otp/__init__.py
otp/admin.py
otp/apps.py
otp/models.py
otp/tests.py
otp/views.py
otp/migrations/0001_initial.py
otp/migrations/0002_auto_20210422_0725.py
otp/migrations/0003_auto_20210422_0754.py
otp/migrations/__init__.py